gm_plotting/__init__.py
gm_plotting/api_client.py
gm_plotting/coords.py
gm_plotting/test_coords.py
gm_plotting-0.1.0.dist-info/LICENSE
gm_plotting-0.1.0.dist-info/WHEEL
gm_plotting-0.1.0.dist-info/METADATA
gm_plotting-0.1.0.dist-info/RECORD
